[
	{
		"key": "datr",
		"value": "p_ADaoCM18O4b69ujEiEsXbH",
		"domain": "facebook.com",
		"path": "/",
		"hostOnly": false,
		"creation": "2026-05-13T06:38:02.943Z",
		"lastAccessed": "2026-05-13T06:38:04.012Z"
	},
	{
		"key": "sb",
		"value": "p_ADatc7F8TwfYIVlKjY5KYh",
		"domain": "facebook.com",
		"path": "/",
		"hostOnly": false,
		"creation": "2026-05-13T06:38:02.944Z",
		"lastAccessed": "2026-05-13T06:38:04.012Z"
	},
	{
		"key": "ps_l",
		"value": "1",
		"domain": "facebook.com",
		"path": "/",
		"hostOnly": false,
		"creation": "2026-05-13T06:38:02.944Z",
		"lastAccessed": "2026-05-13T06:38:04.012Z"
	},
	{
		"key": "ps_n",
		"value": "1",
		"domain": "facebook.com",
		"path": "/",
		"hostOnly": false,
		"creation": "2026-05-13T06:38:02.944Z",
		"lastAccessed": "2026-05-13T06:38:04.012Z"
	},
	{
		"key": "locale",
		"value": "ar_AR",
		"domain": "facebook.com",
		"path": "/",
		"hostOnly": false,
		"creation": "2026-05-13T06:38:02.944Z",
		"lastAccessed": "2026-05-13T06:38:04.012Z"
	},
	{
		"key": "vpd",
		"value": "v1%3B758x412x1.75",
		"domain": "facebook.com",
		"path": "/",
		"hostOnly": false,
		"creation": "2026-05-13T06:38:02.944Z",
		"lastAccessed": "2026-05-13T06:38:04.012Z"
	},
	{
		"key": "dpr",
		"value": "1.75",
		"domain": "facebook.com",
		"path": "/",
		"hostOnly": false,
		"creation": "2026-05-13T06:38:02.944Z",
		"lastAccessed": "2026-05-13T06:38:04.012Z"
	},
	{
		"key": "m_pixel_ratio",
		"value": "1.75",
		"domain": "facebook.com",
		"path": "/",
		"hostOnly": false,
		"creation": "2026-05-13T06:38:02.944Z",
		"lastAccessed": "2026-05-13T06:38:04.012Z"
	},
	{
		"key": "pas",
		"value": "61589118706395%3AEGt1QSWCxT",
		"domain": "facebook.com",
		"path": "/",
		"hostOnly": false,
		"creation": "2026-05-13T06:38:02.944Z",
		"lastAccessed": "2026-05-13T06:38:04.012Z"
	},
	{
		"key": "wl_cbv",
		"value": "v2%3Bclient_version%3A3158%3Btimestamp%3A1778652602",
		"domain": "facebook.com",
		"path": "/",
		"hostOnly": false,
		"creation": "2026-05-13T06:38:02.944Z",
		"lastAccessed": "2026-05-13T06:38:04.012Z"
	},
	{
		"key": "oo",
		"value": "v1",
		"expires": "2027-06-17T06:37:58.000Z",
		"domain": "facebook.com",
		"path": "/",
		"hostOnly": false,
		"creation": "2026-05-13T06:38:02.945Z",
		"lastAccessed": "2026-05-13T06:38:04.012Z"
	},
	{
		"key": "wd",
		"value": "980x1804",
		"domain": "facebook.com",
		"path": "/",
		"hostOnly": false,
		"creation": "2026-05-13T06:38:02.945Z",
		"lastAccessed": "2026-05-13T06:38:04.012Z"
	},
	{
		"key": "c_user",
		"value": "61589320452763",
		"domain": "facebook.com",
		"path": "/",
		"hostOnly": false,
		"creation": "2026-05-13T06:38:02.945Z",
		"lastAccessed": "2026-05-13T06:38:04.012Z"
	},
	{
		"key": "xs",
		"value": "15%3At8w0tQBzO2kD5A%3A2%3A1778652899%3A-1%3A-1%3A%3AAczxIJeF2HZrhFEL3uvqIBIroecSD7qgPoE_bgQlYA",
		"domain": "facebook.com",
		"path": "/",
		"hostOnly": false,
		"creation": "2026-05-13T06:38:02.945Z",
		"lastAccessed": "2026-05-13T06:38:04.012Z"
	},
	{
		"key": "fr",
		"value": "0eMyVvBx5MHkMLQTG.AWfNI_EcdpyPZiY8MNMqSM9O2wMtHXtbL1h0hpox6a-UgBp_nLk.BqBBxG..AAA.0.0.BqBBxL.AWcfkXcJsBh2OlAVNl1QvvTQYrw",
		"expires": "2026-08-11T06:38:03.000Z",
		"maxAge": 7776000,
		"domain": "facebook.com",
		"path": "/",
		"secure": true,
		"httpOnly": true,
		"extensions": [
			"SameSite=None"
		],
		"hostOnly": false,
		"creation": "2026-05-13T06:38:02.945Z",
		"lastAccessed": "2026-05-13T06:38:04.012Z"
	},
	{
		"key": "datr",
		"value": "p_ADaoCM18O4b69ujEiEsXbH",
		"domain": "facebook.com",
		"path": "/",
		"hostOnly": false,
		"creation": "2026-05-13T06:38:02.943Z",
		"lastAccessed": "2026-05-13T06:38:04.012Z"
	},
	{
		"key": "sb",
		"value": "p_ADatc7F8TwfYIVlKjY5KYh",
		"domain": "facebook.com",
		"path": "/",
		"hostOnly": false,
		"creation": "2026-05-13T06:38:02.944Z",
		"lastAccessed": "2026-05-13T06:38:04.012Z"
	},
	{
		"key": "ps_l",
		"value": "1",
		"domain": "facebook.com",
		"path": "/",
		"hostOnly": false,
		"creation": "2026-05-13T06:38:02.944Z",
		"lastAccessed": "2026-05-13T06:38:04.012Z"
	},
	{
		"key": "ps_n",
		"value": "1",
		"domain": "facebook.com",
		"path": "/",
		"hostOnly": false,
		"creation": "2026-05-13T06:38:02.944Z",
		"lastAccessed": "2026-05-13T06:38:04.012Z"
	},
	{
		"key": "locale",
		"value": "ar_AR",
		"domain": "facebook.com",
		"path": "/",
		"hostOnly": false,
		"creation": "2026-05-13T06:38:02.944Z",
		"lastAccessed": "2026-05-13T06:38:04.012Z"
	},
	{
		"key": "vpd",
		"value": "v1%3B758x412x1.75",
		"domain": "facebook.com",
		"path": "/",
		"hostOnly": false,
		"creation": "2026-05-13T06:38:02.944Z",
		"lastAccessed": "2026-05-13T06:38:04.012Z"
	},
	{
		"key": "dpr",
		"value": "1.75",
		"domain": "facebook.com",
		"path": "/",
		"hostOnly": false,
		"creation": "2026-05-13T06:38:02.944Z",
		"lastAccessed": "2026-05-13T06:38:04.012Z"
	},
	{
		"key": "m_pixel_ratio",
		"value": "1.75",
		"domain": "facebook.com",
		"path": "/",
		"hostOnly": false,
		"creation": "2026-05-13T06:38:02.944Z",
		"lastAccessed": "2026-05-13T06:38:04.012Z"
	},
	{
		"key": "pas",
		"value": "61589118706395%3AEGt1QSWCxT",
		"domain": "facebook.com",
		"path": "/",
		"hostOnly": false,
		"creation": "2026-05-13T06:38:02.944Z",
		"lastAccessed": "2026-05-13T06:38:04.012Z"
	},
	{
		"key": "wl_cbv",
		"value": "v2%3Bclient_version%3A3158%3Btimestamp%3A1778652602",
		"domain": "facebook.com",
		"path": "/",
		"hostOnly": false,
		"creation": "2026-05-13T06:38:02.944Z",
		"lastAccessed": "2026-05-13T06:38:04.012Z"
	},
	{
		"key": "oo",
		"value": "v1",
		"expires": "2027-06-17T06:37:58.000Z",
		"domain": "facebook.com",
		"path": "/",
		"hostOnly": false,
		"creation": "2026-05-13T06:38:02.945Z",
		"lastAccessed": "2026-05-13T06:38:04.012Z"
	},
	{
		"key": "wd",
		"value": "980x1804",
		"domain": "facebook.com",
		"path": "/",
		"hostOnly": false,
		"creation": "2026-05-13T06:38:02.945Z",
		"lastAccessed": "2026-05-13T06:38:04.012Z"
	},
	{
		"key": "c_user",
		"value": "61589320452763",
		"domain": "facebook.com",
		"path": "/",
		"hostOnly": false,
		"creation": "2026-05-13T06:38:02.945Z",
		"lastAccessed": "2026-05-13T06:38:04.012Z"
	},
	{
		"key": "xs",
		"value": "15%3At8w0tQBzO2kD5A%3A2%3A1778652899%3A-1%3A-1%3A%3AAczxIJeF2HZrhFEL3uvqIBIroecSD7qgPoE_bgQlYA",
		"domain": "facebook.com",
		"path": "/",
		"hostOnly": false,
		"creation": "2026-05-13T06:38:02.945Z",
		"lastAccessed": "2026-05-13T06:38:04.012Z"
	},
	{
		"key": "fr",
		"value": "0eMyVvBx5MHkMLQTG.AWfNI_EcdpyPZiY8MNMqSM9O2wMtHXtbL1h0hpox6a-UgBp_nLk.BqBBxG..AAA.0.0.BqBBxL.AWcfkXcJsBh2OlAVNl1QvvTQYrw",
		"expires": "2026-08-11T06:38:03.000Z",
		"maxAge": 7776000,
		"domain": "facebook.com",
		"path": "/",
		"secure": true,
		"httpOnly": true,
		"extensions": [
			"SameSite=None"
		],
		"hostOnly": false,
		"creation": "2026-05-13T06:38:02.945Z",
		"lastAccessed": "2026-05-13T06:38:04.012Z"
	},
	{
		"key": "oo",
		"value": "v1",
		"expires": "2027-06-17T06:37:58.000Z",
		"domain": "messenger.com",
		"path": "/",
		"hostOnly": false,
		"creation": "2026-05-13T06:38:02.945Z",
		"lastAccessed": "2026-05-13T06:38:04.012Z"
	},
	{
		"key": "fr",
		"value": "0eMyVvBx5MHkMLQTG.AWfNI_EcdpyPZiY8MNMqSM9O2wMtHXtbL1h0hpox6a-UgBp_nLk.BqBBxG..AAA.0.0.BqBBxL.AWcfkXcJsBh2OlAVNl1QvvTQYrw",
		"expires": "2026-08-11T06:38:03.000Z",
		"maxAge": 7776000,
		"domain": "messenger.com",
		"path": "/",
		"secure": true,
		"httpOnly": true,
		"extensions": [
			"SameSite=None"
		],
		"hostOnly": false,
		"creation": "2026-05-13T06:38:02.945Z",
		"lastAccessed": "2026-05-13T06:38:04.012Z"
	}
]